<?xml version="1.0" standalone="no"?>
<source_library title="source library">
    <source name="ComaBerenices" type="PointSource" tscalc="1" >
        <spectrum type="FileFunction" file="$MYXMLS/DMSpectrum/annihilation/ComaBerenices/tau/ComaBerenices_Anna_Tau_10000GeV.txt">
            <parameter scale="1.0" name="Normalization" min="0.0" max="1.e+10" value="1.0" free="1"/>
        </spectrum>
        <spatialModel type="PointSource" >
            <parameter name="RA"  scale="1.0" value="186.746" min="-360" max="360" free="0" />
            <parameter name="DEC" scale="1.0" value="23.904" min="-90" max="90" free="0" />
        </spatialModel>
    </source>
    <source name="CTABackgroundModel" type="CTAIrfBackground" instrument="CTA">
        <spectrum type="PowerLaw">
            <parameter name="Prefactor" value="1" error="0" scale="1" min="0.001" max="1000" free="1" />
            <parameter name="Index" value="0" error="0" scale="1" min="-5" max="5" free="1" />
            <parameter name="Scale" value="1" scale="1000000" min="0.01" max="1000" free="0" />
        </spectrum>
    </source>
</source_library>
